<?xml version="1.0" encoding="UTF-8"?>
<beans xmlns="http://www.springframework.org/schema/beans"
    xmlns:xsi="http://www.w3.org/2001/XMLSchema-instance" xmlns:context="http://www.springframework.org/schema/context"
    xmlns:tx="http://www.springframework.org/schema/tx" xmlns:aop="http://www.springframework.org/schema/aop"
    xsi:schemaLocation="
    http://www.springframework.org/schema/tx
    http://www.springframework.org/schema/tx/spring-tx-4.0.xsd
    http://www.springframework.org/schema/beans
    http://www.springframework.org/schema/beans/spring-beans-4.0.xsd
    http://www.springframework.org/schema/context
    http://www.springframework.org/schema/context/spring-context-4.0.xsd">
    <context:annotation-config />
    <context:property-placeholder location="classpath:/connection.properties" />

    <import resource="classpath:./core-context.xml" />

    <context:component-scan base-package="com.excilys.dao.impl" />

    <bean id="txManager"
        class="org.springframework.orm.hibernate5.HibernateTransactionManager">
        <property name="sessionFactory" ref="sessionFactory" />
    </bean>

    <tx:annotation-driven transaction-manager="txManager" />

    <bean id="sessionFactory"
        class="org.springframework.orm.hibernate5.LocalSessionFactoryBean">
        <property name="dataSource" ref="dataSource" />
        <property name="packagesToScan" value="com.excilys.model" />
        <property name="hibernateProperties">
            <props>
                <prop key="hibernate.id.new_generator_mappings">false</prop>
                <prop key="hibernate.dialect">org.hibernate.dialect.MySQLDialect</prop>
                <prop key="hibernate.show_sql">false</prop>
            </props>
        </property>
    </bean>

    <bean id="dataSource"
        class="org.springframework.jdbc.datasource.DriverManagerDataSource">
        <property name="driverClassName" value="${driver}" />
        <property name="url" value="${url}" />
        <property name="username" value="${nomutilisateur}" />
        <property name="password" value="${motdepasse}" />
    </bean>
</beans>
